tablemango/__init__.py
tablemango/tablemango.py
tablemango23-0.2.dist-info/LICENSE
tablemango23-0.2.dist-info/METADATA
tablemango23-0.2.dist-info/WHEEL
tablemango23-0.2.dist-info/top_level.txt
tablemango23-0.2.dist-info/RECORD
